{
    "Week 20": {
        "Aai Kuthe Kay Karte": {
            "TRP": 42.1,
            "Rank": 1
        },
        "Rang Majha Vegla": {
            "TRP": 40.3,
            "Rank": 2
        },
        "Sukh Mhanje Nakki Kay Asta": {
            "TRP": 39.7,
            "Rank": 3
        },
        "Thipkyanchi Rangoli": {
            "TRP": 36.5,
            "Rank": 4
        },
        "Majhi Tujhi Reshimgath": {
            "TRP": 34.2,
            "Rank": 5
        },
        "Phulala Sugandh Maticha": {
            "TRP": 33.8,
            "Rank": 6
        },
        "Man Udu Udu Jhala": {
            "TRP": 32.0,
            "Rank": 7
        },
        "Swabhimaan": {
            "TRP": 30.3,
            "Rank": 8
        },
        "Lagnachi Bedi": {
            "TRP": 29.6,
            "Rank": 9
        },
        "Tujhech Mi Geet Gaat Ahe": {
            "TRP": 27.5,
            "Rank": 10
        }
    }
}